credalabs_python_toolbox/__init__.py
credalabs_python_toolbox-0.4.0.dist-info/METADATA
credalabs_python_toolbox-0.4.0.dist-info/WHEEL
credalabs_python_toolbox-0.4.0.dist-info/top_level.txt
credalabs_python_toolbox-0.4.0.dist-info/RECORD
