Metadata-Version: 2.4
Name: credalabs-python-toolbox
Version: 0.4.0
Summary: We want to provide basic tools for our day-to-day work.
Author: graph@credalabs.one
Requires-Python: <4,>=3.11
Requires-Dist: poetry==2.1.1
Provides-Extra: nvim
Requires-Dist: pynvim==0.5.2; extra == "nvim"
Provides-Extra: debug
Requires-Dist: debugpy==1.8.14; extra == "debug"
Provides-Extra: lint
Requires-Dist: black==24.2.0; extra == "lint"
Requires-Dist: isort==5.13.2; extra == "lint"
Requires-Dist: nbqa==1.9.1; extra == "lint"
Provides-Extra: notebook
Requires-Dist: nbstripout==0.8.1; extra == "notebook"
Requires-Dist: jupytext==1.17.0; extra == "notebook"
Requires-Dist: ipykernel==6.29.5; extra == "notebook"
Provides-Extra: tests
Requires-Dist: coverage==7.8.2; extra == "tests"
